simplay/__init__.py
simplay/components.py
simplay/core.py
simplay/events.py
simplay/primitives.py
simplay/visualization.py
simplay-1.0.1.dist-info/METADATA
simplay-1.0.1.dist-info/WHEEL
simplay-1.0.1.dist-info/licenses/LICENSE
simplay-1.0.1.dist-info/RECORD
